pydal2sql_core/__about__.py
pydal2sql_core/__init__.py
pydal2sql_core/cli_support.py
pydal2sql_core/core.py
pydal2sql_core/helpers.py
pydal2sql_core/py.typed
pydal2sql_core/types.py
pydal2sql_core-0.4.0.dist-info/METADATA
pydal2sql_core-0.4.0.dist-info/WHEEL
pydal2sql_core-0.4.0.dist-info/licenses/LICENSE.txt
pydal2sql_core-0.4.0.dist-info/RECORD
