Metadata-Version: 2.3
Name: pydal2sql-core
Version: 0.4.0
Summary: CLI-agnostic pydal2sql code; Convert pydal define_tables to SQL using pydal's CREATE TABLE logic.
Project-URL: Documentation, https://github.com/robinvandernoord/pydal2sql-core#readme
Project-URL: Issues, https://github.com/robinvandernoord/pydal2sql-core/issues
Project-URL: Source, https://github.com/robinvandernoord/pydal2sql-core
Author-email: Robin van der Noord <robinvandernoord@gmail.com>
License-Expression: MIT
License-File: LICENSE.txt
Keywords: databases,pydal,sql
Classifier: Development Status :: 4 - Beta
Classifier: Programming Language :: Python
Classifier: Programming Language :: Python :: 3.10
Classifier: Programming Language :: Python :: 3.11
Classifier: Programming Language :: Python :: 3.12
Classifier: Programming Language :: Python :: Implementation :: CPython
Classifier: Programming Language :: Python :: Implementation :: PyPy
Requires-Python: >=3.10
Requires-Dist: black
Requires-Dist: gitpython
Requires-Dist: pydal
Requires-Dist: rich
Requires-Dist: witchery>=0.2.0
Provides-Extra: all
Requires-Dist: psycopg2-binary; extra == 'all'
Requires-Dist: pymysql; extra == 'all'
Requires-Dist: typedal; extra == 'all'
Provides-Extra: dev
Requires-Dist: contextlib-chdir; extra == 'dev'
Requires-Dist: hatch; extra == 'dev'
Requires-Dist: psycopg2-binary; extra == 'dev'
Requires-Dist: pymysql; extra == 'dev'
Requires-Dist: python-semantic-release<8; extra == 'dev'
Requires-Dist: su6[all]; extra == 'dev'
Requires-Dist: typedal; extra == 'dev'
Provides-Extra: mysql
Requires-Dist: pymysql; extra == 'mysql'
Provides-Extra: psql
Requires-Dist: psycopg2-binary; extra == 'psql'
Provides-Extra: typedal
Requires-Dist: typedal; extra == 'typedal'
